{
    "devops": {
        "time_run": [
            28.7,
            25.95,
            25.96,
            26.05,
            26.05
        ],
        "time_avg": 26.54,
        "metrics_sec": [
            3035882,
            3357496,
            3356408,
            3344789,
            3345354
        ],
        "total_metrics": 87130600,
        "metrics_avg": 3287985,
        "rows_sec": [
            270907,
            299606,
            299509,
            298472,
            298523
        ],
        "total_rows": 7775100,
        "rows_avg": 293403
    },
    "iot": {
        "time_run": [
            24.45,
            23.34,
            21.79,
            21.45,
            22.62
        ],
        "time_avg": 22.73,
        "metrics_sec": [
            5056094,
            5296308,
            5673730,
            5764220,
            5464810
        ],
        "total_metrics": 123624840,
        "metrics_avg": 5451032,
        "rows_sec": [
            636240,
            666467,
            713961,
            725348,
            687671
        ],
        "total_rows": 15556484,
        "rows_avg": 685937
    },
    "metadata": {
        "db_engine": "questdb",
        "scale": 1000,
        "seed": 123,
        "workers": 20,
        "runs": 5,
        "start_date": "2024-09-01"
    }
}